{
    "bombProb": 0.15,
    "hexProb": 0.825,
    "niceness": 0.24080000000000001,
    "pushInterval": 5,
    "row1": [
        "gray",
        "gray",
        "pink",
        "blue",
        "blue",
        "blue",
        "yellow",
        "yellow",
        "yellow"
    ],
    "row10": [
        "gray",
        "yellow",
        "blue",
        "green",
        "green",
        "green",
        "yellow",
        "gray",
        "gray"
    ],
    "row11": [
        "red",
        "yellow",
        "blue",
        "blue",
        "pink",
        "pink",
        "yellow",
        "yellow",
        "gray"
    ],
    "row12": [
        "pink",
        "yellow",
        "green",
        "blue",
        "pink",
        "red",
        "pink",
        "blue",
        "yellow"
    ],
    "row13": [
        "pink",
        "blue",
        "green",
        "gray",
        "red",
        "pink",
        "red",
        "pink",
        "blue"
    ],
    "row14": [
        "blue",
        "pink",
        "blue",
        "pink",
        "pink",
        "gray",
        "gray",
        "gray",
        "pink"
    ],
    "row15": [
        "gray",
        "red",
        "blue",
        "pink",
        "pink",
        "green",
        "yellow",
        "gray",
        "yellow"
    ],
    "row16": [
        "gray",
        "gray",
        "yellow",
        "pink",
        "blue",
        "yellow",
        "red",
        "green",
        "yellow"
    ],
    "row17": [
        "green",
        "pink",
        "blue",
        "blue",
        "green",
        "gray",
        "gray",
        "green",
        "yellow"
    ],
    "row18": [
        "red",
        "yellow",
        "gray",
        "yellow",
        "yellow",
        "gray",
        "yellow",
        "blue",
        "red"
    ],
    "row19": [
        "red",
        "gray",
        "gray",
        "blue",
        "gray",
        "yellow",
        "yellow",
        "green",
        "yellow"
    ],
    "row2": [
        "gray",
        "green",
        "green",
        "gray",
        "blue",
        "pink",
        "pink",
        "gray",
        "yellow"
    ],
    "row20": [
        "green",
        "gray",
        "yellow",
        "pink",
        "gray",
        "gray",
        "gray",
        "yellow",
        "gray"
    ],
    "row3": [
        "green",
        "blue",
        "pink",
        "blue",
        "blue",
        "pink",
        "red",
        "gray",
        "gray"
    ],
    "row4": [
        "green",
        "blue",
        "gray",
        "red",
        "red",
        "blue",
        "blue",
        "green",
        "gray"
    ],
    "row5": [
        "gray",
        "yellow",
        "gray",
        "pink",
        "yellow",
        "red",
        "red",
        "blue",
        "red"
    ],
    "row6": [
        "pink",
        "green",
        "yellow",
        "red",
        "yellow",
        "red",
        "pink",
        "yellow",
        "blue"
    ],
    "row7": [
        "blue",
        "green",
        "yellow",
        "yellow",
        "yellow",
        "pink",
        "green",
        "gray",
        "blue"
    ],
    "row8": [
        "gray",
        "green",
        "green",
        "pink",
        "gray",
        "pink",
        "blue",
        "blue",
        "pink"
    ],
    "row9": [
        "gray",
        "yellow",
        "pink",
        "pink",
        "pink",
        "green",
        "blue",
        "blue",
        "green"
    ],
    "superProb": 0.025,
    "target": 1150
}