{
    "bombProb": 0.21664,
    "hexProb": 0.76504,
    "niceness": 0.2384,
    "pushInterval": 7,
    "row1": [
        "gray",
        "gray",
        "green",
        "gray",
        "yellow",
        "yellow",
        "yellow",
        "blue",
        "blue"
    ],
    "row10": [
        "blue",
        "green",
        "gray",
        "pink",
        "pink",
        "pink",
        "green",
        "red",
        "pink"
    ],
    "row11": [
        "red",
        "blue",
        "gray",
        "blue",
        "red",
        "yellow",
        "pink",
        "blue",
        "red"
    ],
    "row12": [
        "gray",
        "pink",
        "gray",
        "blue",
        "blue",
        "gray",
        "pink",
        "pink",
        "pink"
    ],
    "row13": [
        "gray",
        "gray",
        "pink",
        "green",
        "green",
        "blue",
        "yellow",
        "pink",
        "blue"
    ],
    "row14": [
        "gray",
        "yellow",
        "yellow",
        "gray",
        "gray",
        "blue",
        "yellow",
        "gray",
        "blue"
    ],
    "row15": [
        "yellow",
        "gray",
        "gray",
        "yellow",
        "green",
        "green",
        "gray",
        "yellow",
        "blue"
    ],
    "row16": [
        "yellow",
        "pink",
        "yellow",
        "gray",
        "yellow",
        "red",
        "blue",
        "green",
        "pink"
    ],
    "row17": [
        "pink",
        "yellow",
        "green",
        "yellow",
        "red",
        "red",
        "red",
        "gray",
        "gray"
    ],
    "row18": [
        "yellow",
        "yellow",
        "yellow",
        "gray",
        "green",
        "red",
        "gray",
        "gray",
        "gray"
    ],
    "row19": [
        "blue",
        "green",
        "pink",
        "pink",
        "pink",
        "yellow",
        "pink",
        "pink",
        "gray"
    ],
    "row2": [
        "red",
        "blue",
        "green",
        "red",
        "yellow",
        "yellow",
        "green",
        "green",
        "yellow"
    ],
    "row20": [
        "blue",
        "gray",
        "yellow",
        "pink",
        "yellow",
        "pink",
        "pink",
        "pink",
        "red"
    ],
    "row3": [
        "pink",
        "blue",
        "yellow",
        "yellow",
        "yellow",
        "green",
        "blue",
        "pink",
        "green"
    ],
    "row4": [
        "gray",
        "yellow",
        "yellow",
        "yellow",
        "yellow",
        "pink",
        "blue",
        "blue",
        "green"
    ],
    "row5": [
        "gray",
        "gray",
        "red",
        "yellow",
        "blue",
        "green",
        "red",
        "yellow",
        "pink"
    ],
    "row6": [
        "pink",
        "gray",
        "gray",
        "red",
        "pink",
        "pink",
        "gray",
        "green",
        "blue"
    ],
    "row7": [
        "blue",
        "green",
        "gray",
        "gray",
        "red",
        "pink",
        "red",
        "gray",
        "gray"
    ],
    "row8": [
        "red",
        "pink",
        "red",
        "red",
        "red",
        "red",
        "green",
        "green",
        "blue"
    ],
    "row9": [
        "pink",
        "yellow",
        "gray",
        "blue",
        "red",
        "red",
        "green",
        "green",
        "pink"
    ],
    "superProb": 0.018320000000000003,
    "target": 1350
}