{
    "bombProb": 0.31336,
    "bossLevel": false,
    "hexProb": 0.6174,
    "niceness": 0.4616,
    "numRows": 20,
    "pushInterval": 15,
    "row1": [
        "yellow",
        "yellow",
        "yellow",
        "yellow",
        "blue",
        "blue",
        "blue",
        "green",
        "green"
    ],
    "row10": [
        "green",
        "pink",
        "pink",
        "pink",
        "blue",
        "gray",
        "gray",
        "gray",
        "gray"
    ],
    "row11": [
        "green",
        "pink",
        "pink",
        "green",
        "red",
        "gray",
        "blue",
        "gray",
        "gray"
    ],
    "row12": [
        "green",
        "green",
        "green",
        "green",
        "blue",
        "gray",
        "gray",
        "gray",
        "gray"
    ],
    "row13": [
        "green",
        "gray",
        "gray",
        "green",
        "blue",
        "gray",
        "gray",
        "green",
        "green"
    ],
    "row14": [
        "yellow",
        "gray",
        "green",
        "green",
        "green",
        "gray",
        "blue",
        "yellow",
        "yellow"
    ],
    "row15": [
        "blue",
        "green",
        "green",
        "green",
        "green",
        "green",
        "pink",
        "green",
        "green"
    ],
    "row16": [
        "green",
        "green",
        "green",
        "green",
        "green",
        "green",
        "yellow",
        "green",
        "green"
    ],
    "row17": [
        "gray",
        "green",
        "green",
        "green",
        "green",
        "pink",
        "red",
        "green",
        "green"
    ],
    "row18": [
        "gray",
        "gray",
        "gray",
        "red",
        "green",
        "green",
        "gray",
        "yellow",
        "green"
    ],
    "row19": [
        "yellow",
        "gray",
        "gray",
        "pink",
        "blue",
        "green",
        "blue",
        "blue",
        "red"
    ],
    "row2": [
        "blue",
        "gray",
        "red",
        "yellow",
        "blue",
        "gray",
        "pink",
        "green",
        "green"
    ],
    "row20": [
        "yellow",
        "gray",
        "gray",
        "gray",
        "yellow",
        "blue",
        "blue",
        "blue",
        "blue"
    ],
    "row3": [
        "blue",
        "pink",
        "pink",
        "blue",
        "blue",
        "blue",
        "blue",
        "gray",
        "gray"
    ],
    "row4": [
        "pink",
        "red",
        "red",
        "blue",
        "blue",
        "red",
        "red",
        "gray",
        "gray"
    ],
    "row5": [
        "pink",
        "pink",
        "pink",
        "blue",
        "blue",
        "red",
        "blue",
        "gray",
        "gray"
    ],
    "row6": [
        "pink",
        "pink",
        "blue",
        "yellow",
        "green",
        "blue",
        "blue",
        "gray",
        "gray"
    ],
    "row7": [
        "gray",
        "pink",
        "pink",
        "gray",
        "pink",
        "red",
        "blue",
        "gray",
        "gray"
    ],
    "row8": [
        "pink",
        "pink",
        "pink",
        "pink",
        "red",
        "red",
        "gray",
        "gray",
        "gray"
    ],
    "row9": [
        "gray",
        "pink",
        "pink",
        "pink",
        "gray",
        "red",
        "gray",
        "gray",
        "gray"
    ],
    "superProb": 0.06924,
    "target": 300
}