{
    "bombProb": 0.2108262840127084,
    "hexProb": 0.7536728485332481,
    "niceness": 0.4592,
    "pushInterval": 9,
    "row1": [
        "blue",
        "blue",
        "pink",
        "green",
        "green",
        "red",
        "green",
        "gray",
        "green"
    ],
    "row10": [
        "yellow",
        "yellow",
        "green",
        "blue",
        "yellow",
        "blue",
        "gray",
        "blue",
        "blue"
    ],
    "row11": [
        "pink",
        "yellow",
        "green",
        "red",
        "red",
        "yellow",
        "yellow",
        "green",
        "yellow"
    ],
    "row12": [
        "gray",
        "green",
        "green",
        "red",
        "red",
        "yellow",
        "pink",
        "yellow",
        "yellow"
    ],
    "row13": [
        "gray",
        "gray",
        "green",
        "green",
        "red",
        "red",
        "gray",
        "green",
        "yellow"
    ],
    "row14": [
        "gray",
        "yellow",
        "blue",
        "yellow",
        "pink",
        "green",
        "blue",
        "green",
        "yellow"
    ],
    "row15": [
        "blue",
        "blue",
        "blue",
        "blue",
        "blue",
        "red",
        "yellow",
        "yellow",
        "yellow"
    ],
    "row16": [
        "blue",
        "blue",
        "blue",
        "pink",
        "blue",
        "blue",
        "yellow",
        "yellow",
        "yellow"
    ],
    "row17": [
        "pink",
        "blue",
        "gray",
        "blue",
        "blue",
        "blue",
        "blue",
        "yellow",
        "yellow"
    ],
    "row18": [
        "pink",
        "pink",
        "pink",
        "blue",
        "blue",
        "green",
        "blue",
        "pink",
        "yellow"
    ],
    "row19": [
        "gray",
        "pink",
        "pink",
        "blue",
        "blue",
        "blue",
        "blue",
        "blue",
        "blue"
    ],
    "row2": [
        "yellow",
        "blue",
        "blue",
        "green",
        "green",
        "green",
        "green",
        "green",
        "green"
    ],
    "row20": [
        "green",
        "pink",
        "pink",
        "blue",
        "blue",
        "gray",
        "gray",
        "blue",
        "green"
    ],
    "row3": [
        "gray",
        "blue",
        "blue",
        "green",
        "green",
        "green",
        "gray",
        "blue",
        "blue"
    ],
    "row4": [
        "blue",
        "blue",
        "blue",
        "pink",
        "gray",
        "green",
        "gray",
        "pink",
        "blue"
    ],
    "row5": [
        "blue",
        "blue",
        "yellow",
        "blue",
        "blue",
        "red",
        "gray",
        "gray",
        "gray"
    ],
    "row6": [
        "red",
        "blue",
        "yellow",
        "green",
        "gray",
        "gray",
        "blue",
        "blue",
        "gray"
    ],
    "row7": [
        "red",
        "red",
        "yellow",
        "yellow",
        "gray",
        "blue",
        "blue",
        "blue",
        "red"
    ],
    "row8": [
        "gray",
        "red",
        "blue",
        "yellow",
        "blue",
        "gray",
        "blue",
        "blue",
        "red"
    ],
    "row9": [
        "yellow",
        "red",
        "blue",
        "blue",
        "blue",
        "blue",
        "blue",
        "blue",
        "blue"
    ],
    "superProb": 0.03550086745404345,
    "target": 250
}