{
    "bombProb": 0.29984,
    "bossLevel": false,
    "hexProb": 0.6355999999999999,
    "niceness": 0.4304,
    "numRows": 23,
    "pushInterval": 14,
    "row1": [
        "green",
        "blue",
        "blue",
        "blue",
        "green",
        "green",
        "pink",
        "pink",
        "blue"
    ],
    "row10": [
        "pink",
        "green",
        "yellow",
        "green",
        "green",
        "blue",
        "yellow",
        "red",
        "red"
    ],
    "row11": [
        "gray",
        "yellow",
        "yellow",
        "yellow",
        "green",
        "green",
        "blue",
        "red",
        "red"
    ],
    "row12": [
        "gray",
        "yellow",
        "yellow",
        "pink",
        "pink",
        "green",
        "red",
        "red",
        "blue"
    ],
    "row13": [
        "gray",
        "yellow",
        "yellow",
        "pink",
        "blue",
        "red",
        "red",
        "red",
        "gray"
    ],
    "row14": [
        "red",
        "blue",
        "blue",
        "blue",
        "blue",
        "red",
        "red",
        "red",
        "gray"
    ],
    "row15": [
        "gray",
        "blue",
        "blue",
        "blue",
        "blue",
        "blue",
        "blue",
        "red",
        "red"
    ],
    "row16": [
        "gray",
        "pink",
        "yellow",
        "red",
        "blue",
        "red",
        "red",
        "pink",
        "pink"
    ],
    "row17": [
        "gray",
        "blue",
        "gray",
        "gray",
        "blue",
        "red",
        "gray",
        "pink",
        "green"
    ],
    "row18": [
        "blue",
        "gray",
        "pink",
        "gray",
        "gray",
        "gray",
        "gray",
        "gray",
        "green"
    ],
    "row19": [
        "blue",
        "blue",
        "blue",
        "blue",
        "red",
        "pink",
        "green",
        "green",
        "green"
    ],
    "row2": [
        "gray",
        "blue",
        "blue",
        "red",
        "red",
        "green",
        "pink",
        "pink",
        "blue"
    ],
    "row20": [
        "pink",
        "pink",
        "green",
        "blue",
        "blue",
        "blue",
        "green",
        "blue",
        "green"
    ],
    "row21": [
        "pink",
        "pink",
        "green",
        "yellow",
        "gray",
        "green",
        "green",
        "green",
        "green"
    ],
    "row22": [
        "pink",
        "yellow",
        "green",
        "green",
        "green",
        "green",
        "green",
        "green",
        "green"
    ],
    "row23": [
        "pink",
        "yellow",
        "blue",
        "pink",
        "gray",
        "green",
        "green",
        "red",
        "red"
    ],
    "row3": [
        "green",
        "green",
        "blue",
        "red",
        "green",
        "green",
        "blue",
        "pink",
        "pink"
    ],
    "row4": [
        "red",
        "green",
        "green",
        "green",
        "green",
        "green",
        "gray",
        "green",
        "red"
    ],
    "row5": [
        "red",
        "green",
        "green",
        "green",
        "yellow",
        "green",
        "gray",
        "gray",
        "blue"
    ],
    "row6": [
        "green",
        "yellow",
        "green",
        "green",
        "pink",
        "green",
        "red",
        "gray",
        "blue"
    ],
    "row7": [
        "green",
        "pink",
        "green",
        "red",
        "pink",
        "pink",
        "red",
        "red",
        "red"
    ],
    "row8": [
        "blue",
        "green",
        "green",
        "green",
        "blue",
        "pink",
        "red",
        "blue",
        "red"
    ],
    "row9": [
        "red",
        "green",
        "green",
        "green",
        "pink",
        "yellow",
        "red",
        "red",
        "red"
    ],
    "superProb": 0.06456,
    "target": 450
}